{
  "config": "forex_end_period",
  "slug": "economy",
  "name": "Monthly Exchange Rates (End Period)",
  "source": "Central Bank of Kenya",
  "description": "Monthly exchange rates of major currencies against KES (end period)",
  "url": "https://www.centralbank.go.ke/uploads/exchange_rates/677633335_Monthly%20exchange%20rate%20(end%20period).csv",
  "row_count": 7970,
  "columns": [
    {
      "name": "year",
      "type": "int64",
      "description": "Calendar year",
      "nullable": false,
      "null_count": 0,
      "non_null_count": 7970,
      "sample_values": [
        1993,
        1993,
        1993,
        1993,
        1993
      ],
      "stats": {
        "count": 7970,
        "mean": 2009.7092848180678,
        "std": 9.575121306755491,
        "min": 1993.0,
        "25%": 2001.0,
        "50%": 2010.0,
        "75%": 2018.0,
        "max": 2026.0
      }
    },
    {
      "name": "month",
      "type": "object",
      "description": "Calendar month name (e.g., January)",
      "nullable": false,
      "null_count": 0,
      "non_null_count": 7970,
      "sample_values": [
        "January",
        "January",
        "January",
        "January",
        "January"
      ],
      "stats": null
    },
    {
      "name": "metric",
      "type": "object",
      "description": "Foreign currency name (e.g., united states dollar, sterling pound)",
      "nullable": false,
      "null_count": 0,
      "non_null_count": 7970,
      "sample_values": [
        "united states dollar",
        "sterling pound",
        "deutch mark",
        "canadian dollar",
        "french franc"
      ],
      "stats": null
    },
    {
      "name": "value",
      "type": "float64",
      "description": "End-period exchange rate in KES per unit of foreign currency (comma-formatted number)",
      "nullable": false,
      "null_count": 0,
      "non_null_count": 7970,
      "sample_values": [
        35.92,
        54.48,
        22.67,
        28.3,
        6.69
      ],
      "stats": {
        "count": 7970,
        "mean": 41.649609786700125,
        "std": 40.28992809183422,
        "min": 1.08,
        "25%": 11.25,
        "50%": 21.7,
        "75%": 70.33500000000001,
        "max": 203.79
      }
    }
  ]
}